{"cameraMode":{"drawMode":0,"name":"Shaded","section":"Shading Mode"},"sceneLighting":true,"audioPlay":false,"sceneViewState":{"showFog":true,"showMaterialUpdate":false,"showSkybox":true,"showFlares":true,"showImageEffects":true,"showParticleSystems":true},"in2DMode":false,"pivot":{"x":50.69856262207031,"y":-4.334611892700195,"z":41.705406188964847},"rotation":{"x":0.5293644070625305,"y":0.06147745996713638,"z":-0.0385005809366703,"w":0.8452882170677185},"size":81.03398895263672,"orthographic":false}